odoo/addons/account_asset_compute_batch/README.rst
odoo/addons/account_asset_compute_batch/__init__.py
odoo/addons/account_asset_compute_batch/__manifest__.py
odoo/addons/account_asset_compute_batch/data/service_cron.xml
odoo/addons/account_asset_compute_batch/i18n/account_asset_compute_batch.pot
odoo/addons/account_asset_compute_batch/i18n/es.po
odoo/addons/account_asset_compute_batch/models/__init__.py
odoo/addons/account_asset_compute_batch/models/account_asset.py
odoo/addons/account_asset_compute_batch/models/account_asset_compute_batch.py
odoo/addons/account_asset_compute_batch/models/account_asset_line.py
odoo/addons/account_asset_compute_batch/models/account_move.py
odoo/addons/account_asset_compute_batch/readme/CONTRIBUTORS.rst
odoo/addons/account_asset_compute_batch/readme/DESCRIPTION.rst
odoo/addons/account_asset_compute_batch/readme/USAGE.rst
odoo/addons/account_asset_compute_batch/security/account_asset_security.xml
odoo/addons/account_asset_compute_batch/security/ir.model.access.csv
odoo/addons/account_asset_compute_batch/static/description/icon.png
odoo/addons/account_asset_compute_batch/static/description/index.html
odoo/addons/account_asset_compute_batch/tests/__init__.py
odoo/addons/account_asset_compute_batch/tests/test_account_asset_compute_batch.py
odoo/addons/account_asset_compute_batch/views/account_asset_compute_batch.xml
odoo/addons/account_asset_compute_batch/wizard/__init__.py
odoo/addons/account_asset_compute_batch/wizard/account_asset_compute.py
odoo/addons/account_asset_compute_batch/wizard/account_asset_compute.xml
odoo14_addon_account_asset_compute_batch-14.0.1.0.1.dist-info/METADATA
odoo14_addon_account_asset_compute_batch-14.0.1.0.1.dist-info/WHEEL
odoo14_addon_account_asset_compute_batch-14.0.1.0.1.dist-info/top_level.txt
odoo14_addon_account_asset_compute_batch-14.0.1.0.1.dist-info/RECORD
